p1exporter/__init__.py
p1exporter/p1collector.py
p1exporter/p1reader.py
p1exporter-0.0.3.data/scripts/p1exporter
p1exporter-0.0.3.dist-info/LICENSE
p1exporter-0.0.3.dist-info/METADATA
p1exporter-0.0.3.dist-info/WHEEL
p1exporter-0.0.3.dist-info/top_level.txt
p1exporter-0.0.3.dist-info/RECORD
