Metadata-Version: 2.1
Name: p1exporter
Version: 0.0.3
Summary: A reader and prometheus exporter for smart meters
Home-page: https://github.com/dvx76/p1exporter
Author: Fabrice Devaux
Author-email: fabrice.devaux@gmail.com
License: UNKNOWN
Project-URL: Bug Tracker, https://github.com/dvx76/p1exporter/issues
Platform: UNKNOWN
Classifier: Programming Language :: Python :: 3
Classifier: License :: OSI Approved :: MIT License
Classifier: Operating System :: OS Independent
Requires-Python: >=3.7
License-File: LICENSE
Requires-Dist: crcmod (>=1.7)
Requires-Dist: prometheus-client (>=0.13.1)
Requires-Dist: pyserial (>=3.5)
Provides-Extra: testing
Requires-Dist: pytest ; extra == 'testing'
